Metadata-Version: 1.0
Name: taxRep
Version: 0.5.3
Summary: Taxonomy of microbial genomes
Home-page: https://github.com/MrOlm/tRep
Author: Matt Olm
Author-email: mattolm@berkeley.edu
License: MIT
Platform: UNKNOWN
